cookiecutter_uv/__init__.py
cookiecutter_uv/cli.py
cookiecutter_uv-0.2.0.dist-info/LICENSE
cookiecutter_uv-0.2.0.dist-info/METADATA
cookiecutter_uv-0.2.0.dist-info/WHEEL
cookiecutter_uv-0.2.0.dist-info/entry_points.txt
cookiecutter_uv-0.2.0.dist-info/top_level.txt
cookiecutter_uv-0.2.0.dist-info/RECORD
