Metadata-Version: 2.1
Name: cookiecutter-uv
Version: 0.2.0
Summary: A python cookiecutter application to create a new python project that uses uv to manage its dependencies.
Author-email: Florian Maas <fpgmaas@gmail.com>
Project-URL: Repository, https://github.com/fpgmaas/cookiecutter-uv
Project-URL: Documentation, https://fpgmaas.github.io/cookiecutter-uv/
Project-URL: Homepage, https://fpgmaas.github.io/cookiecutter-uv/
Keywords: cookiecutter,template,uv
Classifier: Development Status :: 4 - Beta
Classifier: Intended Audience :: Developers
Classifier: License :: OSI Approved :: MIT License
Classifier: Programming Language :: Python
Classifier: Programming Language :: Python :: 3
Classifier: Programming Language :: Python :: 3.8
Classifier: Programming Language :: Python :: 3.9
Classifier: Programming Language :: Python :: 3.10
Classifier: Programming Language :: Python :: 3.11
Classifier: Programming Language :: Python :: 3.12
Classifier: Topic :: Software Development :: Libraries :: Python Modules
Classifier: Topic :: Software Development :: Code Generators
Requires-Python: <4.0,>=3.8
License-File: LICENSE
Requires-Dist: cookiecutter >=2.1.1
